yui/__init__.py
yui/images/ico/airplane.ico
yui/images/ico/calc.ico
yui/images/ico/circle_cube2.ico
yui/images/ico/dcube.ico
yui/images/ico/fap.ico
yui/images/ico/ndas.ico
yui/images/ico/ndw.ico
yui/images/png/3_.png
yui/images/png/3dots_h.png
yui/images/png/3dots_v.png
yui/images/png/3i.png
yui/images/png/4_dots.png
yui/images/png/4_square.png
yui/images/png/add_subs.png
yui/images/png/addgreen.png
yui/images/png/appicon.png
yui/images/png/ar_arrow.png
yui/images/png/ar_check.png
yui/images/png/arrow_cursor.png
yui/images/png/attach.png
yui/images/png/back.png
yui/images/png/ball.png
yui/images/png/ball2.png
yui/images/png/ball_blue.png
yui/images/png/ball_bullet.png
yui/images/png/ball_darkred.png
yui/images/png/ball_golden.png
yui/images/png/ball_green.png
yui/images/png/ball_light.png
yui/images/png/ball_red.png
yui/images/png/biz_1.png
yui/images/png/biz_2.png
yui/images/png/blue_star.png
yui/images/png/bulb.png
yui/images/png/bullet1.png
yui/images/png/bullet1_golden.png
yui/images/png/bullet2.png
yui/images/png/bullet2_golden.png
yui/images/png/bullet3.png
yui/images/png/bullet3_golden.png
yui/images/png/bullet4.png
yui/images/png/calc.png
yui/images/png/calendar.png
yui/images/png/cancel.png
yui/images/png/chart.png
yui/images/png/chart_bar.png
yui/images/png/chart_line.png
yui/images/png/chart_linebar.png
yui/images/png/chart_pie.png
yui/images/png/chat.png
yui/images/png/check.png
yui/images/png/check_sheet.png
yui/images/png/circle_cube.png
yui/images/png/circle_cube2.png
yui/images/png/clip_board.png
yui/images/png/close.png
yui/images/png/close_x.png
yui/images/png/continue.png
yui/images/png/contract.png
yui/images/png/contract_2.png
yui/images/png/cube4.png
yui/images/png/custom.png
yui/images/png/custom_care.png
yui/images/png/custom_money.png
yui/images/png/db.png
yui/images/png/dcube.png
yui/images/png/diamond.png
yui/images/png/doc.png
yui/images/png/doc2.png
yui/images/png/doc_percent.png
yui/images/png/doc_rpt.png
yui/images/png/download.png
yut_jy_tao-0.2.9.dist-info/METADATA
yut_jy_tao-0.2.9.dist-info/WHEEL
yut_jy_tao-0.2.9.dist-info/RECORD
