Metadata-Version: 2.3
Name: yut.jy.tao
Version: 0.2.9
Summary: 通用工具
Author: tjy
Author-email: tjy@yeah.net
Requires-Python: >=3.12
Classifier: Programming Language :: Python :: 3
Classifier: Programming Language :: Python :: 3.12
Classifier: Programming Language :: Python :: 3.13
Project-URL: Homepage, https://gitee.com/jy_tao/yut
